PlasmaPhysics/__init__.py
PlasmaPhysics/_version.py
PlasmaPhysics/dispersion.py
PlasmaPhysics/distributions.py
PlasmaPhysics/formulary.py
PlasmaPhysics/particles.py
PlasmaPhysics/setup.py
PlasmaPhysics/unitsystems.py
PlasmaPhysics/dbutils/NIST.py
PlasmaPhysics/dbutils/__init__.py
PlasmaPhysics/electromagnetism/__init__.py
PlasmaPhysics/electromagnetism/magnetostatics.py
PlasmaPhysics/geometry/__init__.py
PlasmaPhysics/geometry/base.py
PlasmaPhysics/geometry/curves.py
PlasmaPhysics/geometry/surface.py
PlasmaPhysics/geometry/volume.py
PlasmaPhysics/utils/__init__.py
PlasmaPhysics/utils/misc.py
PlasmaPhysics-0.0.0.dev2.dist-info/LICENSE
PlasmaPhysics-0.0.0.dev2.dist-info/METADATA
PlasmaPhysics-0.0.0.dev2.dist-info/WHEEL
PlasmaPhysics-0.0.0.dev2.dist-info/top_level.txt
PlasmaPhysics-0.0.0.dev2.dist-info/RECORD
